nestview/__init__.py
nestview/nv.py
tests/__init__.py
tests/test_nv.py
nestview-0.1.1.dist-info/LICENSE
nestview-0.1.1.dist-info/METADATA
nestview-0.1.1.dist-info/WHEEL
nestview-0.1.1.dist-info/top_level.txt
nestview-0.1.1.dist-info/RECORD
