Metadata-Version: 2.1
Name: nestview
Version: 0.1.1
Summary: Explore nested structures -- dictionaries and lists
Home-page: https://github.com/wojcikk2903/nestview
Author: Krzysztof Wójcik
Author-email: wojcikk2903@gmail.com
License: MIT
Platform: UNKNOWN
Classifier: Development Status :: 3 - Alpha
Classifier: Intended Audience :: Developers
Classifier: Topic :: Utilities
Classifier: License :: OSI Approved :: MIT License
Classifier: Operating System :: OS Independent
Classifier: Programming Language :: Python :: 3
Classifier: Programming Language :: Python :: 3.7
Requires-Dist: singledispatch
